minet/__init__.py
minet/__version__.py
minet/constants.py
minet/cookies.py
minet/dates.py
minet/encodings.py
minet/exceptions.py
minet/executors.py
minet/extraction.py
minet/fs.py
minet/headers.py
minet/heuristics.py
minet/loggers.py
minet/multiprocessing.py
minet/pycurl.py
minet/rate_limiting.py
minet/serialization.py
minet/sqlar.py
minet/types.py
minet/utils.py
minet/web.py
minet/bluesky/__init__.py
minet/bluesky/constants.py
minet/bluesky/exceptions.py
minet/bluesky/http_client.py
minet/bluesky/jwt.py
minet/bluesky/types.py
minet/bluesky/urls.py
minet/bluesky/websocket_client.py
minet/browser/__init__.py
minet/browser/constants.py
minet/browser/extensions.py
minet/browser/plawright_shim.py
minet/browser/threadsafe_browser.py
minet/browser/utils.py
minet/cli/__init__.py
minet/cli/__main__.py
minet/cli/argparse.py
minet/cli/commands.py
minet/cli/console.py
minet/cli/constants.py
minet/cli/exceptions.py
minet/cli/loading_bar.py
minet/cli/reporters.py
minet/cli/run.py
minet/cli/utils.py
minet/cli/bluesky/__init__.py
minet/cli/bluesky/firehose.py
minet/cli/bluesky/search_posts.py
minet/cli/bluesky/utils.py
minet/cli/cookies/__init__.py
minet/cli/cookies/cookies.py
minet/cli/crawl/__init__.py
minet/cli/crawl/crawl.py
minet/cli/crawl/focus.py
minet/cli/dump/__init__.py
minet/cli/dump/dump_graph.py
minet/cli/dump/dump_queue.py
minet/cli/dump/dump_urls.py
minet/cli/extract/__init__.py
minet/cli/extract/extract.py
minet/cli/facebook/__init__.py
minet/cli/facebook/experimental_comments.py
minet/cli/facebook/url_likes.py
minet/cli/fetch/__init__.py
minet/cli/fetch/fetch.py
minet/cli/google/__init__.py
minet/cli/google/sheets.py
minet/cli/hyphe/__init__.py
minet/cli/hyphe/crawl.py
minet/cli/hyphe/declare.py
minet/cli/hyphe/destroy.py
minet/cli/hyphe/dump.py
minet/cli/hyphe/reset.py
minet/cli/hyphe/tag.py
minet/cli/hyphe/utils.py
minet/cli/instagram/__init__.py
minet/cli/instagram/comments.py
minet/cli/instagram/hashtag.py
minet/cli/instagram/location.py
minet-4.1.2.dist-info/LICENSE.txt
minet-4.1.2.dist-info/METADATA
minet-4.1.2.dist-info/WHEEL
minet-4.1.2.dist-info/entry_points.txt
minet-4.1.2.dist-info/top_level.txt
minet-4.1.2.dist-info/zip-safe
minet-4.1.2.dist-info/RECORD
