Metadata-Version: 2.1
Name: minet
Version: 4.1.2
Summary: A webmining CLI tool & library for python.
Home-page: http://github.com/medialab/minet
Author: Guillaume Plique, Pauline Breteau, Jules Farjas, Héloïse Théro, Jean Descamps, Amélie Pellé, Laura Miguel, César Pichon, Kelly Christensen, Julien Pontoire, Béatrice Mazoyer
License: GPL-3.0
Keywords: webmining
Requires-Python: >=3.8
License-File: LICENSE.txt
Requires-Dist: about-time<5,>=4
Requires-Dist: beautifulsoup4<5,>=4.7.1
Requires-Dist: browser-cookie3==0.19.1
Requires-Dist: casanova<3,>=2.0.1
Requires-Dist: charset-normalizer<4,>=3
Requires-Dist: dateparser>=1.1.1
Requires-Dist: ebbe<2,>=1.14
Requires-Dist: json5>=0.8.5
Requires-Dist: libipld<4,>=3
Requires-Dist: nanoid<3,>=2
Requires-Dist: playwright<1.47,>=1.46
Requires-Dist: playwright-stealth<2,>=1.0.6
Requires-Dist: pyyaml
Requires-Dist: quenouille<2,>=1.9.1
Requires-Dist: rich<14,>=13
Requires-Dist: rich-argparse<2,>=1
Requires-Dist: soupsieve<3,>=2.1
Requires-Dist: tenacity<9,>=8
Requires-Dist: trafilatura<2.1,>=2
Requires-Dist: twitter==2.0a2
Requires-Dist: twitwi<0.21,>=0.20
Requires-Dist: ural<2,>=1.5.0
Requires-Dist: urllib3<2,>=1.26.16
Requires-Dist: websockets<14,>=13
Requires-Dist: lxml>=5.3.0; platform_system != "Darwin" or python_version > "3.8"
Requires-Dist: lxml==4.9.2; platform_system == "Darwin" and python_version <= "3.8"
Requires-Dist: typing-extensions>=4.3; python_version < "3.11"
